{
  "code": 0,
  "msg": "成功",
  "data": {
    "nodes": [
      {
        "id": "1734120835608735745",
        "routeIndex": null,
        "name": "MU",
        "sn": "TEST_SIMULATOR9-LTE",
        "alarmCount": 0,
        "criticalCount": null,
        "majorCount": null,
        "minorCount": null,
        "warningCount": null,
        "locked": false,
        "neStatus": "NO_ALARM",
        "neType": "MU",
        "stype": 0
      },
      {
        "id": "1734120835612930049",
        "routeIndex": null,
        "name": "EU_3",
        "sn": "TEST_SIMULATOR9LTE3",
        "alarmCount": 0,
        "criticalCount": null,
        "majorCount": null,
        "minorCount": null,
        "warningCount": null,
        "locked": false,
        "neStatus": "NO_ALARM",
        "neType": "EU",
        "stype": 0
      },
      {
        "id": "1734120835617124353",
        "routeIndex": null,
        "name": "RU_3_5",
        "sn": "TEST_SIMULATOR9LTE35",
        "alarmCount": 0,
        "criticalCount": null,
        "majorCount": null,
        "minorCount": null,
        "warningCount": null,
        "locked": false,
        "neStatus": "NO_ALARM",
        "neType": "RU",
        "stype": 0
      },
      {
        "id": "1734120835617124354",
        "routeIndex": null,
        "name": "RU_3_7",
        "sn": "TEST_SIMULATOR9LTE37",
        "alarmCount": 0,
        "criticalCount": null,
        "majorCount": null,
        "minorCount": null,
        "warningCount": null,
        "locked": false,
        "neStatus": "NO_ALARM",
        "neType": "RU",
        "stype": 0
      },
      {
        "id": "1734120835621318658",
        "routeIndex": null,
        "name": "RU_3_4",
        "sn": "TEST_SIMULATOR9LTE34",
        "alarmCount": 0,
        "criticalCount": null,
        "majorCount": null,
        "minorCount": null,
        "warningCount": null,
        "locked": false,
        "neStatus": "NO_ALARM",
        "neType": "RU",
        "stype": 0
      },
      {
        "id": "1734120835625512961",
        "routeIndex": null,
        "name": "RU_3_6",
        "sn": "TEST_SIMULATOR9LTE36",
        "alarmCount": 0,
        "criticalCount": null,
        "majorCount": null,
        "minorCount": null,
        "warningCount": null,
        "locked": false,
        "neStatus": "NO_ALARM",
        "neType": "RU",
        "stype": 0
      },
      {
        "id": "1734120835629707265",
        "routeIndex": null,
        "name": "RU_3_2",
        "sn": "TEST_SIMULATOR9LTE32",
        "alarmCount": 0,
        "criticalCount": null,
        "majorCount": null,
        "minorCount": null,
        "warningCount": null,
        "locked": false,
        "neStatus": "NO_ALARM",
        "neType": "RU",
        "stype": 0
      },
      {
        "id": "1734120835638095874",
        "routeIndex": null,
        "name": "RU_3_8",
        "sn": "TEST_SIMULATOR9LTE38",
        "alarmCount": 0,
        "criticalCount": null,
        "majorCount": null,
        "minorCount": null,
        "warningCount": null,
        "locked": false,
        "neStatus": "NO_ALARM",
        "neType": "RU",
        "stype": 0
      },
      {
        "id": "1734120835638095875",
        "routeIndex": null,
        "name": "RU_3_1",
        "sn": "TEST_SIMULATOR9LTE31",
        "alarmCount": 0,
        "criticalCount": null,
        "majorCount": null,
        "minorCount": null,
        "warningCount": null,
        "locked": false,
        "neStatus": "NO_ALARM",
        "neType": "RU",
        "stype": 0
      },
      {
        "id": "1734120835638095876",
        "routeIndex": null,
        "name": "RU_3_3",
        "sn": "TEST_SIMULATOR9LTE33",
        "alarmCount": 0,
        "criticalCount": null,
        "majorCount": null,
        "minorCount": null,
        "warningCount": null,
        "locked": false,
        "neStatus": "NO_ALARM",
        "neType": "RU",
        "stype": 0
      },
      {
        "id": "1734120835642290177",
        "routeIndex": null,
        "name": "EU_4",
        "sn": "TEST_SIMULATOR9LTE4",
        "alarmCount": 0,
        "criticalCount": null,
        "majorCount": null,
        "minorCount": null,
        "warningCount": null,
        "locked": false,
        "neStatus": "NO_ALARM",
        "neType": "EU",
        "stype": 0
      },
      {
        "id": "1734120835642290178",
        "routeIndex": null,
        "name": "RU_4_5",
        "sn": "TEST_SIMULATOR9LTE45",
        "alarmCount": 0,
        "criticalCount": null,
        "majorCount": null,
        "minorCount": null,
        "warningCount": null,
        "locked": false,
        "neStatus": "NO_ALARM",
        "neType": "RU",
        "stype": 0
      },
      {
        "id": "1734120835680038913",
        "routeIndex": null,
        "name": "RU_4_7",
        "sn": "TEST_SIMULATOR9LTE47",
        "alarmCount": 0,
        "criticalCount": null,
        "majorCount": null,
        "minorCount": null,
        "warningCount": null,
        "locked": false,
        "neStatus": "NO_ALARM",
        "neType": "RU",
        "stype": 0
      },
      {
        "id": "1734120835684233218",
        "routeIndex": null,
        "name": "RU_4_1",
        "sn": "TEST_SIMULATOR9LTE41",
        "alarmCount": 0,
        "criticalCount": null,
        "majorCount": null,
        "minorCount": null,
        "warningCount": null,
        "locked": false,
        "neStatus": "NO_ALARM",
        "neType": "RU",
        "stype": 0
      },
      {
        "id": "1734120835684233219",
        "routeIndex": null,
        "name": "RU_4_2",
        "sn": "TEST_SIMULATOR9LTE42",
        "alarmCount": 0,
        "criticalCount": null,
        "majorCount": null,
        "minorCount": null,
        "warningCount": null,
        "locked": false,
        "neStatus": "NO_ALARM",
        "neType": "RU",
        "stype": 0
      },
      {
        "id": "1734120835684233220",
        "routeIndex": null,
        "name": "RU_4_8",
        "sn": "TEST_SIMULATOR9LTE48",
        "alarmCount": 0,
        "criticalCount": null,
        "majorCount": null,
        "minorCount": null,
        "warningCount": null,
        "locked": false,
        "neStatus": "NO_ALARM",
        "neType": "RU",
        "stype": 0
      },
      {
        "id": "1734120835688427522",
        "routeIndex": null,
        "name": "RU_4_6",
        "sn": "TEST_SIMULATOR9LTE46",
        "alarmCount": 0,
        "criticalCount": null,
        "majorCount": null,
        "minorCount": null,
        "warningCount": null,
        "locked": false,
        "neStatus": "NO_ALARM",
        "neType": "RU",
        "stype": 0
      },
      {
        "id": "1734120835688427523",
        "routeIndex": null,
        "name": "RU_4_3",
        "sn": "TEST_SIMULATOR9LTE43",
        "alarmCount": 0,
        "criticalCount": null,
        "majorCount": null,
        "minorCount": null,
        "warningCount": null,
        "locked": false,
        "neStatus": "NO_ALARM",
        "neType": "RU",
        "stype": 0
      },
      {
        "id": "1734120835688427524",
        "routeIndex": null,
        "name": "RU_4_4",
        "sn": "TEST_SIMULATOR9LTE44",
        "alarmCount": 0,
        "criticalCount": null,
        "majorCount": null,
        "minorCount": null,
        "warningCount": null,
        "locked": false,
        "neStatus": "NO_ALARM",
        "neType": "RU",
        "stype": 0
      },
      {
        "id": "1734120835688427525",
        "routeIndex": null,
        "name": "EU_2",
        "sn": "TEST_SIMULATOR9LTE2",
        "alarmCount": 0,
        "criticalCount": null,
        "majorCount": null,
        "minorCount": null,
        "warningCount": null,
        "locked": false,
        "neStatus": "NO_ALARM",
        "neType": "EU",
        "stype": 0
      },
      {
        "id": "1734120835692621825",
        "routeIndex": null,
        "name": "RU_2_5",
        "sn": "TEST_SIMULATOR9LTE25",
        "alarmCount": 0,
        "criticalCount": null,
        "majorCount": null,
        "minorCount": null,
        "warningCount": null,
        "locked": false,
        "neStatus": "NO_ALARM",
        "neType": "RU",
        "stype": 0
      },
      {
        "id": "1734120835696816129",
        "routeIndex": null,
        "name": "RU_2_3",
        "sn": "TEST_SIMULATOR9LTE23",
        "alarmCount": 0,
        "criticalCount": null,
        "majorCount": null,
        "minorCount": null,
        "warningCount": null,
        "locked": false,
        "neStatus": "NO_ALARM",
        "neType": "RU",
        "stype": 0
      },
      {
        "id": "1734120835696816130",
        "routeIndex": null,
        "name": "RU_2_8",
        "sn": "TEST_SIMULATOR9LTE28",
        "alarmCount": 0,
        "criticalCount": null,
        "majorCount": null,
        "minorCount": null,
        "warningCount": null,
        "locked": false,
        "neStatus": "NO_ALARM",
        "neType": "RU",
        "stype": 0
      },
      {
        "id": "1734120835696816131",
        "routeIndex": null,
        "name": "RU_2_4",
        "sn": "TEST_SIMULATOR9LTE24",
        "alarmCount": 0,
        "criticalCount": null,
        "majorCount": null,
        "minorCount": null,
        "warningCount": null,
        "locked": false,
        "neStatus": "NO_ALARM",
        "neType": "RU",
        "stype": 0
      },
      {
        "id": "1734120835696816132",
        "routeIndex": null,
        "name": "RU_2_7",
        "sn": "TEST_SIMULATOR9LTE27",
        "alarmCount": 0,
        "criticalCount": null,
        "majorCount": null,
        "minorCount": null,
        "warningCount": null,
        "locked": false,
        "neStatus": "NO_ALARM",
        "neType": "RU",
        "stype": 0
      },
      {
        "id": "1734120835701010434",
        "routeIndex": null,
        "name": "RU_2_2",
        "sn": "TEST_SIMULATOR9LTE22",
        "alarmCount": 0,
        "criticalCount": null,
        "majorCount": null,
        "minorCount": null,
        "warningCount": null,
        "locked": false,
        "neStatus": "NO_ALARM",
        "neType": "RU",
        "stype": 0
      },
      {
        "id": "1734120835701010435",
        "routeIndex": null,
        "name": "RU_2_1",
        "sn": "TEST_SIMULATOR9LTE21",
        "alarmCount": 0,
        "criticalCount": null,
        "majorCount": null,
        "minorCount": null,
        "warningCount": null,
        "locked": false,
        "neStatus": "NO_ALARM",
        "neType": "RU",
        "stype": 0
      },
      {
        "id": "1734120835701010436",
        "routeIndex": null,
        "name": "RU_2_6",
        "sn": "TEST_SIMULATOR9LTE26",
        "alarmCount": 0,
        "criticalCount": null,
        "majorCount": null,
        "minorCount": null,
        "warningCount": null,
        "locked": false,
        "neStatus": "NO_ALARM",
        "neType": "RU",
        "stype": 0
      },
      {
        "id": "1734120835705204737",
        "routeIndex": null,
        "name": "EU_1",
        "sn": "TEST_SIMULATOR9LTE1",
        "alarmCount": 0,
        "criticalCount": null,
        "majorCount": null,
        "minorCount": null,
        "warningCount": null,
        "locked": false,
        "neStatus": "NO_ALARM",
        "neType": "EU",
        "stype": 0
      },
      {
        "id": "1734120835705204738",
        "routeIndex": null,
        "name": "RU_1_7",
        "sn": "TEST_SIMULATOR9LTE17",
        "alarmCount": 0,
        "criticalCount": null,
        "majorCount": null,
        "minorCount": null,
        "warningCount": null,
        "locked": false,
        "neStatus": "NO_ALARM",
        "neType": "RU",
        "stype": 0
      },
      {
        "id": "1734120835709399041",
        "routeIndex": null,
        "name": "RU_1_8",
        "sn": "TEST_SIMULATOR9LTE18",
        "alarmCount": 0,
        "criticalCount": null,
        "majorCount": null,
        "minorCount": null,
        "warningCount": null,
        "locked": false,
        "neStatus": "NO_ALARM",
        "neType": "RU",
        "stype": 0
      },
      {
        "id": "1734120835709399042",
        "routeIndex": null,
        "name": "RU_1_1",
        "sn": "TEST_SIMULATOR9LTE11",
        "alarmCount": 0,
        "criticalCount": null,
        "majorCount": null,
        "minorCount": null,
        "warningCount": null,
        "locked": false,
        "neStatus": "NO_ALARM",
        "neType": "RU",
        "stype": 0
      },
      {
        "id": "1734120835713593345",
        "routeIndex": null,
        "name": "RU_1_3",
        "sn": "TEST_SIMULATOR9LTE13",
        "alarmCount": 0,
        "criticalCount": null,
        "majorCount": null,
        "minorCount": null,
        "warningCount": null,
        "locked": false,
        "neStatus": "NO_ALARM",
        "neType": "RU",
        "stype": 0
      },
      {
        "id": "1734120835713593346",
        "routeIndex": null,
        "name": "RU_1_5",
        "sn": "TEST_SIMULATOR9LTE15",
        "alarmCount": 0,
        "criticalCount": null,
        "majorCount": null,
        "minorCount": null,
        "warningCount": null,
        "locked": false,
        "neStatus": "NO_ALARM",
        "neType": "RU",
        "stype": 0
      },
      {
        "id": "1734120835713593347",
        "routeIndex": null,
        "name": "RU_1_2",
        "sn": "TEST_SIMULATOR9LTE12",
        "alarmCount": 0,
        "criticalCount": null,
        "majorCount": null,
        "minorCount": null,
        "warningCount": null,
        "locked": false,
        "neStatus": "NO_ALARM",
        "neType": "RU",
        "stype": 0
      },
      {
        "id": "1734120835717787649",
        "routeIndex": null,
        "name": "RU_1_4",
        "sn": "TEST_SIMULATOR9LTE14",
        "alarmCount": 0,
        "criticalCount": null,
        "majorCount": null,
        "minorCount": null,
        "warningCount": null,
        "locked": false,
        "neStatus": "NO_ALARM",
        "neType": "RU",
        "stype": 0
      },
      {
        "id": "1734120835717787650",
        "routeIndex": null,
        "name": "RU_1_6",
        "sn": "TEST_SIMULATOR9LTE16",
        "alarmCount": 0,
        "criticalCount": null,
        "majorCount": null,
        "minorCount": null,
        "warningCount": null,
        "locked": false,
        "neStatus": "NO_ALARM",
        "neType": "RU",
        "stype": 0
      },
      {
        "id": "1734120835717787651",
        "routeIndex": null,
        "name": "RRU_1_1",
        "sn": "123456",
        "alarmCount": 0,
        "criticalCount": null,
        "majorCount": null,
        "minorCount": null,
        "warningCount": null,
        "locked": false,
        "neStatus": "NO_ALARM",
        "neType": "RRU",
        "stype": 0
      }
    ],
    "links": [
      {
        "src": "1734120835608735745",
        "dst": "1734120835612930049"
      },
      {
        "src": "1734120835612930049",
        "dst": "1734120835617124353"
      },
      {
        "src": "1734120835612930049",
        "dst": "1734120835617124354"
      },
      {
        "src": "1734120835612930049",
        "dst": "1734120835621318658"
      },
      {
        "src": "1734120835612930049",
        "dst": "1734120835625512961"
      },
      {
        "src": "1734120835612930049",
        "dst": "1734120835629707265"
      },
      {
        "src": "1734120835612930049",
        "dst": "1734120835638095874"
      },
      {
        "src": "1734120835612930049",
        "dst": "1734120835638095875"
      },
      {
        "src": "1734120835612930049",
        "dst": "1734120835638095876"
      },
      {
        "src": "1734120835608735745",
        "dst": "1734120835642290177"
      },
      {
        "src": "1734120835642290177",
        "dst": "1734120835642290178"
      },
      {
        "src": "1734120835642290177",
        "dst": "1734120835680038913"
      },
      {
        "src": "1734120835642290177",
        "dst": "1734120835684233218"
      },
      {
        "src": "1734120835642290177",
        "dst": "1734120835684233219"
      },
      {
        "src": "1734120835642290177",
        "dst": "1734120835684233220"
      },
      {
        "src": "1734120835642290177",
        "dst": "1734120835688427522"
      },
      {
        "src": "1734120835642290177",
        "dst": "1734120835688427523"
      },
      {
        "src": "1734120835642290177",
        "dst": "1734120835688427524"
      },
      {
        "src": "1734120835608735745",
        "dst": "1734120835688427525"
      },
      {
        "src": "1734120835688427525",
        "dst": "1734120835692621825"
      },
      {
        "src": "1734120835688427525",
        "dst": "1734120835696816129"
      },
      {
        "src": "1734120835688427525",
        "dst": "1734120835696816130"
      },
      {
        "src": "1734120835688427525",
        "dst": "1734120835696816131"
      },
      {
        "src": "1734120835688427525",
        "dst": "1734120835696816132"
      },
      {
        "src": "1734120835688427525",
        "dst": "1734120835701010434"
      },
      {
        "src": "1734120835688427525",
        "dst": "1734120835701010435"
      },
      {
        "src": "1734120835688427525",
        "dst": "1734120835701010436"
      },
      {
        "src": "1734120835608735745",
        "dst": "1734120835705204737"
      },
      {
        "src": "1734120835705204737",
        "dst": "1734120835705204738"
      },
      {
        "src": "1734120835705204737",
        "dst": "1734120835709399041"
      },
      {
        "src": "1734120835705204737",
        "dst": "1734120835709399042"
      },
      {
        "src": "1734120835705204737",
        "dst": "1734120835713593345"
      },
      {
        "src": "1734120835705204737",
        "dst": "1734120835713593346"
      },
      {
        "src": "1734120835705204737",
        "dst": "1734120835713593347"
      },
      {
        "src": "1734120835705204737",
        "dst": "1734120835717787649"
      },
      {
        "src": "1734120835705204737",
        "dst": "1734120835717787650"
      },
      {
        "src": "1734120835608735745",
        "dst": "1734120835717787651"
      }
    ],
    "stationName": "4G微站-9",
    "gId": "99994444",
    "gType": 4
  }
}
